async_claude_client/__init__.py
async_claude_client/claude_ai/__init__.py
async_claude_client/claude_ai/client.py
async_claude_client/claude_ai/const.py
async_claude_client/claude_ai/util.py
async_claude_client/slack_claude/__init__.py
async_claude_client/slack_claude/client.py
async_claude_client/slack_claude/types.py
async_claude_client/util.py
async_claude_client-0.1.3.dist-info/METADATA
async_claude_client-0.1.3.dist-info/WHEEL
async_claude_client-0.1.3.dist-info/RECORD
