Metadata-Version: 2.1
Name: async-claude-client
Version: 0.1.3
Summary: async client for claude.ai and slack.com
Home-page: https://github.com/canxin121/Async-Claude-Client
Author: canxin
Author-email: 1969730106@qq.com
Requires-Python: >=3.8,<4.0
Classifier: Programming Language :: Python :: 3
Classifier: Programming Language :: Python :: 3.8
Classifier: Programming Language :: Python :: 3.9
Classifier: Programming Language :: Python :: 3.10
Classifier: Programming Language :: Python :: 3.11
Requires-Dist: curl-cffi (>=0.5.7,<0.6.0)
Requires-Dist: loguru (>=0.7.1,<0.8.0)
Requires-Dist: pydantic (>=1.10.12,<2.0.0)
Requires-Dist: slack-sdk (>=3.21.3,<4.0.0)
